{
	"id": "2702da50-a327-4e55-b268-ca5d1a901fd1",
	"name": "PressAndPlay",
	"values": [
		{
			"key": "baseUrl",
			"value": "http://loclhost:5000",
			"type": "default",
			"enabled": true
		},
		{
			"key": "lastUserID",
			"value": "",
			"type": "any",
			"enabled": true
		},
		{
			"key": "userSessionID",
			"value": "",
			"type": "any",
			"enabled": true
		}
	],
	"_postman_variable_scope": "environment",
	"_postman_exported_at": "2022-12-08T23:06:55.293Z",
	"_postman_exported_using": "Postman/10.5.8"
}